{
	"ident": 1016,
	"order": 1,
	"objtype": "kComponent",
	"componentlib": "Gantt",
	"componentctrl": "GanttUI",
	"properties": {
		"active": true,
		"alpha": 255,
		"calborder": "kBorderShadow",
		"calbordercolor": "RGB(217,230,255)",
		"calfillcolor": "RGB(217,230,255)",
		"calfontname": 4,
		"calfontsize": 10,
		"calfontstyle": "kPlain",
		"calheight": 40,
		"candropcursor": 0,
		"contextmenu": "",
		"cursor": 0,
		"ddwhere": "kGanttDropNowhere",
		"desgroup": 0,
		"designactive": true,
		"deslock": false,
		"disablefocus": false,
		"disablesystemfocus": false,
		"dragborder": false,
		"dragiconid": 0,
		"dragmode": "kNoDragging",
		"dragrange": "kRangeAll",
		"dropmode": "kAcceptAll",
		"edgefloat": "kEFposnClient",
		"effect": "kBorderNone",
		"enabled": true,
		"fieldstyle": "",
		"gbarstyle": "kGanttBarWash12",
		"gddcandrop": "kGanttCanDropBetweenRows,kGanttCanDropOnRow,kGanttCanDropOnPhase",
		"gdrawjsttext": false,
		"gfontname": 4,
		"gfontsize": 10,
		"gfontstyle": "kPlain",
		"gnoduration": false,
		"gnorelations": false,
		"gphasecandrop": false,
		"grcurvedrawbox": false,
		"grcurvesum": false,
		"grellinestyle": 3,
		"gridhlinecolor": "kGray",
		"gridhlinestyle": 1,
		"gridvlinecolor": "kGray",
		"gridvlinestyle": 1,
		"growheight": 20,
		"grscalecolor": "kDarkRed",
		"grscalefontname": 3,
		"grscalefontsize": 10,
		"grscalefontstyle": "kItalic",
		"gshowhlines": true,
		"gshowvlines": true,
		"headborder": "kBorderShadow",
		"headbordercolor": "RGB(217,230,255)",
		"headfillcolor": "RGB(217,230,255)",
		"headfontname": 4,
		"headfontsize": 12,
		"headfontstyle": "kBold,kItalic",
		"headheight": 40,
		"height": 551,
		"helpfile": 0,
		"hourmovement": false,
		"keyevents": false,
		"left": 0,
		"majorscaledateformat": "",
		"majorscaleshowyear": true,
		"minorscalecolwidth": 30,
		"minorscaledateformat": "",
		"mouseevents": false,
		"nodropcursor": 0,
		"numdecimal": 0,
		"objlink": 0,
		"rmouseevents": false,
		"showdiagram": false,
		"showselline": true,
		"showtotsection": false,
		"splitterhpos": 363,
		"splittervpos": 494,
		"statusevents": false,
		"swapclientarea": false,
		"tlddcandrop": "kGanttCanDropBetweenRows,kGanttCanDropOnRow",
		"tlexpandicon": 10002,
		"tlfontname": 4,
		"tlfontsize": 10,
		"tlfontstyle": "kPlain",
		"tlrealrowheight": 20,
		"tlrowheight": 20,
		"tlshowhlines": true,
		"tlshowvlines": false,
		"tooltip": "",
		"top": 0,
		"totcalclist": "",
		"userinfo": "",
		"visible": true,
		"width": 1315
	}
}
